{
    "id": null,
    "systemId": null,
    "parentId": null,
    "name": ".",
    "lifecycleState": null,
    "isTerminalNode": null,
    "categoryImage": null,
    "text": null,
    "expanded": false,
    "IsTerminal": "0",
    "children": [
        {
            "id": "D22AEAAD89434274ABC687373E5F0CB7",
            "systemId": "D22AEAAD89434274ABC687373E5F0CB7",
            "parentId": "",
            "name": "Root",
            "lifecycleState": "New",
            "isTerminalNode": "0",
            "categoryImage": "",
            "text": "Root",
            "expanded": true,
            "IsTerminal": null,
            "children": [
                {
                    "id": "165C92A8DC24439E978B7D440C79D1FA",
                    "systemId": "165C92A8DC24439E978B7D440C79D1FA",
                    "parentId": "D22AEAAD89434274ABC687373E5F0CB7",
                    "name": "Purchase Order Item",
                    "lifecycleState": "New",
                    "isTerminalNode": "0",
                    "categoryImage": "",
                    "text": "Purchase Order Item",
                    "expanded": false,
                    "IsTerminal": null,
                    "children": []
                },
                {
                    "id": "58DFD82DFF2340F18E9E9C589D5B2CA1",
                    "systemId": "58DFD82DFF2340F18E9E9C589D5B2CA1",
                    "parentId": "D22AEAAD89434274ABC687373E5F0CB7",
                    "name": "qwerty",
                    "lifecycleState": "New",
                    "isTerminalNode": "0",
                    "categoryImage": "",
                    "text": "qwerty",
                    "expanded": false,
                    "IsTerminal": null,
                    "children": []
                },
                {
                    "id": "6BF688B48E77454CB514CAFD0468E863",
                    "systemId": "6BF688B48E77454CB514CAFD0468E863",
                    "parentId": "D22AEAAD89434274ABC687373E5F0CB7",
                    "name": "Module Sets",
                    "lifecycleState": "New",
                    "isTerminalNode": "0",
                    "categoryImage": "",
                    "text": "Module Sets",
                    "expanded": false,
                    "IsTerminal": null,
                    "children": []
                },
                {
                    "id": "900CEE2FA6AC4B40853AF476013C1ADF",
                    "systemId": "900CEE2FA6AC4B40853AF476013C1ADF",
                    "parentId": "D22AEAAD89434274ABC687373E5F0CB7",
                    "name": "Module Systems",
                    "lifecycleState": "New",
                    "isTerminalNode": "0",
                    "categoryImage": "",
                    "text": "Module Systems",
                    "expanded": false,
                    "IsTerminal": null,
                    "children": []
                },
                {
                    "id": "B9D59328B68345FF896BD0D142007BDF",
                    "systemId": "B9D59328B68345FF896BD0D142007BDF",
                    "parentId": "D22AEAAD89434274ABC687373E5F0CB7",
                    "name": "Testing",
                    "lifecycleState": "New",
                    "isTerminalNode": "0",
                    "categoryImage": "",
                    "text": "Testing",
                    "expanded": false,
                    "IsTerminal": null,
                    "children": []
                },
                {
                    "id": "C0DA7C2396F2424A8AF1A133981C2074",
                    "systemId": "C0DA7C2396F2424A8AF1A133981C2074",
                    "parentId": "D22AEAAD89434274ABC687373E5F0CB7",
                    "name": "Vendor",
                    "lifecycleState": "New",
                    "isTerminalNode": "0",
                    "categoryImage": "",
                    "text": "Vendor",
                    "expanded": false,
                    "IsTerminal": null,
                    "children": []
                },
                {
                    "id": "C2062473B2D74B3FBC802F670E4E337B",
                    "systemId": "C2062473B2D74B3FBC802F670E4E337B",
                    "parentId": "D22AEAAD89434274ABC687373E5F0CB7",
                    "name": "Modules",
                    "lifecycleState": "New",
                    "isTerminalNode": "0",
                    "categoryImage": "",
                    "text": "Modules",
                    "expanded": false,
                    "IsTerminal": null,
                    "children": []
                },
                {
                    "id": "CFB39751B9FE497EB9934BA57CE22382",
                    "systemId": "CFB39751B9FE497EB9934BA57CE22382",
                    "parentId": "D22AEAAD89434274ABC687373E5F0CB7",
                    "name": "Parts",
                    "lifecycleState": "New",
                    "isTerminalNode": "0",
                    "categoryImage": "",
                    "text": "Parts",
                    "expanded": false,
                    "IsTerminal": null,
                    "children": [
                        {
                            "id": "56C30F150FD442C9A0B2072B2F04006F",
                            "systemId": "56C30F150FD442C9A0B2072B2F04006F",
                            "parentId": "CFB39751B9FE497EB9934BA57CE22382",
                            "name": "Mechanical",
                            "lifecycleState": "New",
                            "isTerminalNode": "0",
                            "categoryImage": "",
                            "text": "Mechanical",
                            "expanded": false,
                            "IsTerminal": null,
                            "children": [
                                {
                                    "id": "0B8A31C704D9457283BC467502EEFC41",
                                    "systemId": "0B8A31C704D9457283BC467502EEFC41",
                                    "parentId": "56C30F150FD442C9A0B2072B2F04006F",
                                    "name": "Handlebars",
                                    "lifecycleState": "New",
                                    "isTerminalNode": "0",
                                    "categoryImage": "",
                                    "text": "Handlebars",
                                    "expanded": false,
                                    "IsTerminal": null,
                                    "children": []
                                },
                                {
                                    "id": "1B6C57B4D6C24B5BA2F1D25ED41F51A8",
                                    "systemId": "1B6C57B4D6C24B5BA2F1D25ED41F51A8",
                                    "parentId": "56C30F150FD442C9A0B2072B2F04006F",
                                    "name": "Wheels and Tires",
                                    "lifecycleState": "New",
                                    "isTerminalNode": "0",
                                    "categoryImage": "",
                                    "text": "Wheels and Tires",
                                    "expanded": false,
                                    "IsTerminal": null,
                                    "children": []
                                },
                                {
                                    "id": "38609AF4AC3A4A71B00041C32F15DB39",
                                    "systemId": "38609AF4AC3A4A71B00041C32F15DB39",
                                    "parentId": "56C30F150FD442C9A0B2072B2F04006F",
                                    "name": "Exhaust",
                                    "lifecycleState": "New",
                                    "isTerminalNode": "0",
                                    "categoryImage": "",
                                    "text": "Exhaust",
                                    "expanded": false,
                                    "IsTerminal": null,
                                    "children": []
                                },
                                {
                                    "id": "5D89822D17D24C6185564F57E53940ED",
                                    "systemId": "5D89822D17D24C6185564F57E53940ED",
                                    "parentId": "56C30F150FD442C9A0B2072B2F04006F",
                                    "name": "Final Drive",
                                    "lifecycleState": "New",
                                    "isTerminalNode": "0",
                                    "categoryImage": "",
                                    "text": "Final Drive",
                                    "expanded": false,
                                    "IsTerminal": null,
                                    "children": []
                                },
                                {
                                    "id": "66E18B9DDA1C4440A63E3BD1AF62E359",
                                    "systemId": "66E18B9DDA1C4440A63E3BD1AF62E359",
                                    "parentId": "56C30F150FD442C9A0B2072B2F04006F",
                                    "name": "Body Panels",
                                    "lifecycleState": "New",
                                    "isTerminalNode": "0",
                                    "categoryImage": "",
                                    "text": "Body Panels",
                                    "expanded": false,
                                    "IsTerminal": null,
                                    "children": []
                                },
                                {
                                    "id": "A14C6DEF5BCD4EB6BECD2840CBB2ECAF",
                                    "systemId": "A14C6DEF5BCD4EB6BECD2840CBB2ECAF",
                                    "parentId": "56C30F150FD442C9A0B2072B2F04006F",
                                    "name": "Motorcycle Transmissions",
                                    "lifecycleState": "New",
                                    "isTerminalNode": "0",
                                    "categoryImage": "",
                                    "text": "Motorcycle Transmissions",
                                    "expanded": false,
                                    "IsTerminal": null,
                                    "children": []
                                },
                                {
                                    "id": "CDC00588B0D649FCA0FF167E32AAA86C",
                                    "systemId": "CDC00588B0D649FCA0FF167E32AAA86C",
                                    "parentId": "56C30F150FD442C9A0B2072B2F04006F",
                                    "name": "Chassis",
                                    "lifecycleState": "New",
                                    "isTerminalNode": "0",
                                    "categoryImage": "",
                                    "text": "Chassis",
                                    "expanded": false,
                                    "IsTerminal": null,
                                    "children": []
                                },
                                {
                                    "id": "D96D82B11F1E4D46940A17021AB09C14",
                                    "systemId": "D96D82B11F1E4D46940A17021AB09C14",
                                    "parentId": "56C30F150FD442C9A0B2072B2F04006F",
                                    "name": "Foot Pegs",
                                    "lifecycleState": "New",
                                    "isTerminalNode": "0",
                                    "categoryImage": "",
                                    "text": "Foot Pegs",
                                    "expanded": false,
                                    "IsTerminal": null,
                                    "children": []
                                },
                                {
                                    "id": "EBA3F179CE8C45BC9CDED731FD2212ED",
                                    "systemId": "EBA3F179CE8C45BC9CDED731FD2212ED",
                                    "parentId": "56C30F150FD442C9A0B2072B2F04006F",
                                    "name": "Mudguards",
                                    "lifecycleState": "New",
                                    "isTerminalNode": "0",
                                    "categoryImage": "",
                                    "text": "Mudguards",
                                    "expanded": false,
                                    "IsTerminal": null,
                                    "children": []
                                },
                                {
                                    "id": "EFD275F00A2042CBABF06F1E08C825B7",
                                    "systemId": "EFD275F00A2042CBABF06F1E08C825B7",
                                    "parentId": "56C30F150FD442C9A0B2072B2F04006F",
                                    "name": "Lights",
                                    "lifecycleState": "New",
                                    "isTerminalNode": "0",
                                    "categoryImage": "",
                                    "text": "Lights",
                                    "expanded": false,
                                    "IsTerminal": null,
                                    "children": []
                                },
                                {
                                    "id": "F47E325901904308B5EECB2FA9863AAA",
                                    "systemId": "F47E325901904308B5EECB2FA9863AAA",
                                    "parentId": "56C30F150FD442C9A0B2072B2F04006F",
                                    "name": "Motorcycle Brakes",
                                    "lifecycleState": "New",
                                    "isTerminalNode": "0",
                                    "categoryImage": "",
                                    "text": "Motorcycle Brakes",
                                    "expanded": false,
                                    "IsTerminal": null,
                                    "children": []
                                },
                                {
                                    "id": "FE01CFDD7356409A9ADE4568103EA566",
                                    "systemId": "FE01CFDD7356409A9ADE4568103EA566",
                                    "parentId": "56C30F150FD442C9A0B2072B2F04006F",
                                    "name": "Motorcycle Engine",
                                    "lifecycleState": "New",
                                    "isTerminalNode": "0",
                                    "categoryImage": "",
                                    "text": "Motorcycle Engine",
                                    "expanded": false,
                                    "IsTerminal": null,
                                    "children": []
                                }
                            ]
                        },
                        {
                            "id": "8A05CEF6FB714312B1170C05484CC878",
                            "systemId": "8A05CEF6FB714312B1170C05484CC878",
                            "parentId": "CFB39751B9FE497EB9934BA57CE22382",
                            "name": "Motorcycle accessories",
                            "lifecycleState": "New",
                            "isTerminalNode": "0",
                            "categoryImage": "",
                            "text": "Motorcycle accessories",
                            "expanded": false,
                            "IsTerminal": null,
                            "children": []
                        },
                        {
                            "id": "A304AE8BF53C4BCB94841C4705F053DC",
                            "systemId": "A304AE8BF53C4BCB94841C4705F053DC",
                            "parentId": "CFB39751B9FE497EB9934BA57CE22382",
                            "name": "Fasteners",
                            "lifecycleState": "New",
                            "isTerminalNode": "0",
                            "categoryImage": "",
                            "text": "Fasteners",
                            "expanded": false,
                            "IsTerminal": null,
                            "children": [
                                {
                                    "id": "3CCD59534A5D46ACA22DB2330535728E",
                                    "systemId": "3CCD59534A5D46ACA22DB2330535728E",
                                    "parentId": "A304AE8BF53C4BCB94841C4705F053DC",
                                    "name": "Bolts",
                                    "lifecycleState": "New",
                                    "isTerminalNode": "0",
                                    "categoryImage": "",
                                    "text": "Bolts",
                                    "expanded": false,
                                    "IsTerminal": null,
                                    "children": [
                                        {
                                            "id": "0E80783C10EB418BB10CAAB77DEA66DC",
                                            "systemId": "0E80783C10EB418BB10CAAB77DEA66DC",
                                            "parentId": "3CCD59534A5D46ACA22DB2330535728E",
                                            "name": "Banjo Bolt",
                                            "lifecycleState": "New",
                                            "isTerminalNode": "0",
                                            "categoryImage": "",
                                            "text": "Banjo Bolt",
                                            "expanded": false,
                                            "IsTerminal": null,
                                            "children": []
                                        },
                                        {
                                            "id": "580D57057C044BFBA94CCD61C9082332",
                                            "systemId": "580D57057C044BFBA94CCD61C9082332",
                                            "parentId": "3CCD59534A5D46ACA22DB2330535728E",
                                            "name": "Flange Hex Bolt",
                                            "lifecycleState": "New",
                                            "isTerminalNode": "0",
                                            "categoryImage": "",
                                            "text": "Flange Hex Bolt",
                                            "expanded": false,
                                            "IsTerminal": null,
                                            "children": []
                                        },
                                        {
                                            "id": "FB1F69DCB4504DADAEEF013D44D448C8",
                                            "systemId": "FB1F69DCB4504DADAEEF013D44D448C8",
                                            "parentId": "3CCD59534A5D46ACA22DB2330535728E",
                                            "name": "Hex Bolt",
                                            "lifecycleState": "In Work",
                                            "isTerminalNode": "0",
                                            "categoryImage": "",
                                            "text": "Hex Bolt",
                                            "expanded": false,
                                            "IsTerminal": null,
                                            "children": []
                                        }
                                    ]
                                }
                            ]
                        },
                        {
                            "id": "AD7EE5484C46489A82AAC518513A8A4F",
                            "systemId": "AD7EE5484C46489A82AAC518513A8A4F",
                            "parentId": "CFB39751B9FE497EB9934BA57CE22382",
                            "name": "Hardware",
                            "lifecycleState": "New",
                            "isTerminalNode": "0",
                            "categoryImage": "",
                            "text": "Hardware",
                            "expanded": false,
                            "IsTerminal": null,
                            "children": [
                                {
                                    "id": "729687B95C95471D93881AE75D357796",
                                    "systemId": "729687B95C95471D93881AE75D357796",
                                    "parentId": "AD7EE5484C46489A82AAC518513A8A4F",
                                    "name": "Eye Bolt",
                                    "lifecycleState": "New",
                                    "isTerminalNode": "0",
                                    "categoryImage": "",
                                    "text": "Eye Bolt",
                                    "expanded": false,
                                    "IsTerminal": null,
                                    "children": []
                                },
                                {
                                    "id": "FEA90F06AB064E0286028D41CE81DDE2",
                                    "systemId": "FEA90F06AB064E0286028D41CE81DDE2",
                                    "parentId": "AD7EE5484C46489A82AAC518513A8A4F",
                                    "name": "Ball Bearing",
                                    "lifecycleState": "New",
                                    "isTerminalNode": "0",
                                    "categoryImage": "",
                                    "text": "Ball Bearing",
                                    "expanded": false,
                                    "IsTerminal": null,
                                    "children": []
                                }
                            ]
                        }
                    ]
                },
                {
                    "id": "ECA507819D0A4EF09FBC4E207C291745",
                    "systemId": "ECA507819D0A4EF09FBC4E207C291745",
                    "parentId": "D22AEAAD89434274ABC687373E5F0CB7",
                    "name": "Purchase Order",
                    "lifecycleState": "New",
                    "isTerminalNode": "0",
                    "categoryImage": "",
                    "text": "Purchase Order",
                    "expanded": false,
                    "IsTerminal": null,
                    "children": []
                }
            ]
        }
    ]
}
